setup.py
jump_1min_manage_ex_forex_next3/__init__.py
jump_1min_manage_ex_forex_next3/jump_1min_manage_ex_forex_next3.py
jump_1min_manage_ex_forex_next3.egg-info/PKG-INFO
jump_1min_manage_ex_forex_next3.egg-info/SOURCES.txt
jump_1min_manage_ex_forex_next3.egg-info/dependency_links.txt
jump_1min_manage_ex_forex_next3.egg-info/not-zip-safe
jump_1min_manage_ex_forex_next3.egg-info/top_level.txt