Metadata-Version: 1.0
Name: jump-1min-manage-ex-forex-next3
Version: 1.41
Summary: jump_1min_manage_ex_forex_next3
Home-page: UNKNOWN
Author: omid
Author-email: UNKNOWN
License: UNKNOWN
Platform: UNKNOWN
